encant/__init__.py
encant/__main__.py
encant-0.0.5.dist-info/LICENSE
encant-0.0.5.dist-info/METADATA
encant-0.0.5.dist-info/WHEEL
encant-0.0.5.dist-info/entry_points.txt
encant-0.0.5.dist-info/top_level.txt
encant-0.0.5.dist-info/RECORD
