Metadata-Version: 2.1
Name: encant
Version: 0.0.5
Summary: Uber simple python version management
Author-email: Aaron Glover <aglove2189@gmail.com>
License-File: LICENSE
Requires-Dist: requests
Provides-Extra: dev
Requires-Dist: pre-commit ; extra == 'dev'
Requires-Dist: black ==23.9.1 ; extra == 'dev'
Requires-Dist: ruff ==0.0.292 ; extra == 'dev'
